tsktimer/__init__.py
tsktimer/example.py
tsktimer/exceptions.py
tsktimer/core/__init__.py
tsktimer/core/context.py
tsktimer/core/decorator.py
tsktimer/core/tsktimer.py
tsktimer/metrics/__init__.py
tsktimer/metrics/export.py
tsktimer/metrics/history.py
tsktimer/metrics/stats.py
tsktimer/utils/__init__.py
tsktimer/utils/formatting.py
tsktimer-0.0.5.dist-info/licenses/LICENSE
tsktimer-0.0.5.dist-info/METADATA
tsktimer-0.0.5.dist-info/WHEEL
tsktimer-0.0.5.dist-info/top_level.txt
tsktimer-0.0.5.dist-info/RECORD
