Metadata-Version: 2.4
Name: tsktimer
Version: 0.0.5
Summary: Simple way to understand the speed of your tasks
Author-email: 1032249184 <1032249184@pfur.ru>, 1132243816 <1132243816@pfur.ru>, 1132246169 <1132246169@pfur.ru>
Maintainer-email: 1132243816 <1132243816@pfur.ru>, 1132246169 <1132246169@pfur.ru>
License: Copyright 2025 HeloHi
Classifier: Programming Language :: Python :: 3
Classifier: Operating System :: OS Independent
Requires-Python: >=3.10
License-File: LICENSE
Provides-Extra: test
Requires-Dist: pytest; extra == "test"
Dynamic: license-file
